[
	{
		"系所名稱":"材料所           MSE",
		"系號":"N5",
		"序號":"012",
		"課程碼":"N570400",
		"分班碼":"empty",
		"班別":"碩博",
		"年級":"empty",
		"類別":"講義",
		"英語授課":"N",
		"課程名稱 (連結課程地圖)":"生醫腐蝕",
		"選必修":"選修",
		"學分":"3",
		"教師姓名 *:主負責老師":"陳瑾惠",
		"已選課人數 ":"17",
		"餘額 ":"32",
		"時間":"[3]1~2 [4]2",
		"教室":"唯農大樓                      7113",
		"備註":"empty",
		"限選條件":"empty",
		"業界專家參與":"否",
		"屬性碼":"MSE5028",
		"跨領域學分學程":"生物科技學程"
	},
	{
		"系所名稱":"材料所           MSE",
		"系號":"N5",
		"序號":"015",
		"課程碼":"N557600",
		"分班碼":"empty",
		"班別":"碩博",
		"年級":"empty",
		"類別":"講義",
		"英語授課":"N",
		"課程名稱 (連結課程地圖)":"電子顯微鏡學",
		"選必修":"選修",
		"學分":"3",
		"教師姓名 *:主負責老師":"林文台",
		"已選課人數 ":"21",
		"餘額 ":"28",
		"時間":"[2]2 [4]3~4",
		"教室":"唯農大樓                      7202",
		"備註":"empty",
		"限選條件":"empty",
		"業界專家參與":"否",
		"屬性碼":"MSE5046",
		"跨領域學分學程":"empty"
	},
	{
		"系所名稱":"材料所           MSE",
		"系號":"N5",
		"序號":"016",
		"課程碼":"N564400",
		"分班碼":"empty",
		"班別":"碩博",
		"年級":"empty",
		"類別":"講義",
		"英語授課":"N",
		"課程名稱 (連結課程地圖)":"表面科學與分析",
		"選必修":"選修",
		"學分":"3",
		"教師姓名 *:主負責老師":"李汝桐",
		"已選課人數 ":"12",
		"餘額 ":"88",
		"時間":"[3]2 [1]3~4",
		"教室":"儀器設備大樓                  95403",
		"備註":"empty",
		"限選條件":"empty",
		"業界專家參與":"否",
		"屬性碼":"MSE5020",
		"跨領域學分學程":"empty"
	},
	{
		"系所名稱":"材料所           MSE",
		"系號":"N5",
		"序號":"017",
		"課程碼":"N559900",
		"分班碼":"empty",
		"班別":"碩博",
		"年級":"empty",
		"類別":"講義",
		"英語授課":"N",
		"課程名稱 (連結課程地圖)":"碳材料概論",
		"選必修":"選修",
		"學分":"3",
		"教師姓名 *:主負責老師":"朱建平",
		"已選課人數 ":"20",
		"餘額 ":"10",
		"時間":"[3]4 [4]3~4",
		"教室":"唯農大樓                      7102",
		"備註":"第一階段不受理選課",
		"限選條件":"第一階段不受理選課",
		"業界專家參與":"否",
		"屬性碼":"MSE5015",
		"跨領域學分學程":"empty"
	},
	{
		"系所名稱":"材料所           MSE",
		"系號":"N5",
		"序號":"024",
		"課程碼":"N571300",
		"分班碼":"empty",
		"班別":"碩博",
		"年級":"empty",
		"類別":"講義",
		"英語授課":"Y",
		"課程名稱 (連結課程地圖)":"高分子化學",
		"選必修":"選修",
		"學分":"3",
		"教師姓名 *:主負責老師":"郭昌恕",
		"已選課人數 ":"8",
		"餘額 ":"7",
		"時間":"[2]3~4 [5]2",
		"教室":"唯農大樓                      7104",
		"備註":"限15人選課",
		"限選條件":"empty",
		"業界專家參與":"否",
		"屬性碼":"MSE5031",
		"跨領域學分學程":"empty"
	},
	{
		"系所名稱":"材料所           MSE",
		"系號":"N5",
		"序號":"025",
		"課程碼":"N571400",
		"分班碼":"empty",
		"班別":"碩博",
		"年級":"empty",
		"類別":"講義",
		"英語授課":"N",
		"課程名稱 (連結課程地圖)":"結構與異向性",
		"選必修":"選修",
		"學分":"3",
		"教師姓名 *:主負責老師":"郭瑞昭",
		"已選課人數 ":"20",
		"餘額 ":"29",
		"時間":"[2]2 [4]5~6",
		"教室":"唯農大樓                      7206",
		"備註":"empty",
		"限選條件":"empty",
		"業界專家參與":"否",
		"屬性碼":"MSE5032",
		"跨領域學分學程":"empty"
	},
	{
		"系所名稱":"材料所           MSE",
		"系號":"N5",
		"序號":"074",
		"課程碼":"N571200",
		"分班碼":"empty",
		"班別":"碩博",
		"年級":"empty",
		"類別":"講義",
		"英語授課":"N",
		"課程名稱 (連結課程地圖)":"奈米陶瓷特論",
		"選必修":"選修",
		"學分":"3",
		"教師姓名 *:主負責老師":"黃肇瑞",
		"已選課人數 ":"10",
		"餘額 ":"額滿",
		"時間":"[5]9~B",
		"教室":"empty",
		"備註":"上課地點:敬三舍1樓研討室",
		"限選條件":"empty",
		"業界專家參與":"否",
		"屬性碼":"MSE5047",
		"跨領域學分學程":"empty"
	},
	{
		"系所名稱":"材料所           MSE",
		"系號":"N5",
		"序號":"100",
		"課程碼":"N550110",
		"分班碼":"1",
		"班別":"碩一",
		"年級":"empty",
		"類別":"研討",
		"英語授課":"N",
		"課程名稱 (連結課程地圖)":"專題討論（一）",
		"選必修":"必修",
		"學分":"1",
		"教師姓名 *:主負責老師":"林光隆 蘇彥勳*",
		"已選課人數 ":"101",
		"餘額 ":"169",
		"時間":"[4]7~8",
		"教室":"測量系館                      經緯廳",
		"備註":"empty",
		"限選條件":"empty",
		"業界專家參與":"是",
		"屬性碼":"MSE5048",
		"跨領域學分學程":"empty"
	},
	{
		"系所名稱":"材料所           MSE",
		"系號":"N5",
		"序號":"101",
		"課程碼":"N550110",
		"分班碼":"2",
		"班別":"博一",
		"年級":"1",
		"類別":"研討",
		"英語授課":"N",
		"課程名稱 (連結課程地圖)":"專題討論（一）",
		"選必修":"必修",
		"學分":"1",
		"教師姓名 *:主負責老師":"林光隆 蘇彥勳*",
		"已選課人數 ":"8",
		"餘額 ":"262",
		"時間":"[4]7~8",
		"教室":"測量系館                      經緯廳",
		"備註":"碩博合班",
		"限選條件":"empty",
		"業界專家參與":"是",
		"屬性碼":"MSE5048",
		"跨領域學分學程":"empty"
	},
	{
		"系所名稱":"材料所           MSE",
		"系號":"N5",
		"序號":"102",
		"課程碼":"N556800",
		"分班碼":"empty",
		"班別":"碩博",
		"年級":"empty",
		"類別":"研討",
		"英語授課":"N",
		"課程名稱 (連結課程地圖)":"專題討論",
		"選必修":"必修",
		"學分":"0",
		"教師姓名 *:主負責老師":"林光隆 蘇彥勳*",
		"已選課人數 ":"16",
		"餘額 ":"254",
		"時間":"[4]7~8",
		"教室":"測量系館                      經緯廳",
		"備註":"碩博三以上選修",
		"限選條件":"empty",
		"業界專家參與":"是",
		"屬性碼":"MSE5049",
		"跨領域學分學程":"empty"
	},
	{
		"系所名稱":"材料所           MSE",
		"系號":"N5",
		"序號":"103",
		"課程碼":"N550600",
		"分班碼":"1",
		"班別":"碩二",
		"年級":"empty",
		"類別":"研討",
		"英語授課":"N",
		"課程名稱 (連結課程地圖)":"專題討論（三）",
		"選必修":"必修",
		"學分":"1",
		"教師姓名 *:主負責老師":"林光隆 蘇彥勳*",
		"已選課人數 ":"75",
		"餘額 ":"195",
		"時間":"[4]7~8",
		"教室":"測量系館                      經緯廳",
		"備註":"碩博合班",
		"限選條件":"empty",
		"業界專家參與":"是",
		"屬性碼":"MSE5050",
		"跨領域學分學程":"empty"
	},
	{
		"系所名稱":"材料所           MSE",
		"系號":"N5",
		"序號":"104",
		"課程碼":"N550600",
		"分班碼":"2",
		"班別":"博二",
		"年級":"empty",
		"類別":"研討",
		"英語授課":"N",
		"課程名稱 (連結課程地圖)":"專題討論（三）",
		"選必修":"必修",
		"學分":"1",
		"教師姓名 *:主負責老師":"林光隆 蘇彥勳*",
		"已選課人數 ":"10",
		"餘額 ":"260",
		"時間":"[4]7~8",
		"教室":"測量系館                      經緯廳",
		"備註":"empty",
		"限選條件":"empty",
		"業界專家參與":"是",
		"屬性碼":"MSE5050",
		"跨領域學分學程":"empty"
	},
	{
		"系所名稱":"材料所           MSE",
		"系號":"N5",
		"序號":"110",
		"課程碼":"N581500",
		"分班碼":"empty",
		"班別":"碩博",
		"年級":"empty",
		"類別":"講義",
		"英語授課":"N",
		"課程名稱 (連結課程地圖)":"鋼鐵製程特論",
		"選必修":"選修",
		"學分":"3",
		"教師姓名 *:主負責老師":"黃文星",
		"已選課人數 ":"85",
		"餘額 ":"額滿",
		"時間":"[1]6~8",
		"教室":"工科系館                      41104",
		"備註":"empty",
		"限選條件":"empty",
		"業界專家參與":"是",
		"屬性碼":"MSE5045",
		"跨領域學分學程":"empty"
	},
	{
		"系所名稱":"材料所           MSE",
		"系號":"N5",
		"序號":"114",
		"課程碼":"N553500",
		"分班碼":"empty",
		"班別":"碩博",
		"年級":"empty",
		"類別":"講義",
		"英語授課":"N",
		"課程名稱 (連結課程地圖)":"原子級模擬特論",
		"選必修":"選修",
		"學分":"3",
		"教師姓名 *:主負責老師":"許文東",
		"已選課人數 ":"8",
		"餘額 ":"28",
		"時間":"[3]8 [5]3~4",
		"教室":"唯農大樓                      7102",
		"備註":"empty",
		"限選條件":"empty",
		"業界專家參與":"否",
		"屬性碼":"MSE5007",
		"跨領域學分學程":"empty"
	},
	{
		"系所名稱":"材料所           MSE",
		"系號":"N5",
		"序號":"118",
		"課程碼":"N572810",
		"分班碼":"empty",
		"班別":"碩博",
		"年級":"empty",
		"類別":"講義",
		"英語授課":"Y",
		"課程名稱 (連結課程地圖)":"基礎材料科學（一）",
		"選必修":"選修",
		"學分":"3",
		"教師姓名 *:主負責老師":"呂國彰",
		"已選課人數 ":"8",
		"餘額 ":"28",
		"時間":"[1]7~8 [4]6",
		"教室":"機械系館                      91205",
		"備註":"empty",
		"限選條件":"empty",
		"業界專家參與":"否",
		"屬性碼":"MSE5041E",
		"跨領域學分學程":"empty"
	},
	{
		"系所名稱":"材料所           MSE",
		"系號":"N5",
		"序號":"126",
		"課程碼":"N554500",
		"分班碼":"empty",
		"班別":"碩博",
		"年級":"empty",
		"類別":"講義",
		"英語授課":"Y",
		"課程名稱 (連結課程地圖)":"組合式材料製程及其應用",
		"選必修":"選修",
		"學分":"3",
		"教師姓名 *:主負責老師":"張高碩",
		"已選課人數 ":"8",
		"餘額 ":"92",
		"時間":"[5]2 [3]3~4",
		"教室":"儀器設備大樓                  95403",
		"備註":"empty",
		"限選條件":"empty",
		"業界專家參與":"否",
		"屬性碼":"MSE5046",
		"跨領域學分學程":"empty"
	},
	{
		"系所名稱":"材料所           MSE",
		"系號":"N5",
		"序號":"127",
		"課程碼":"N566700",
		"分班碼":"empty",
		"班別":"碩博",
		"年級":"empty",
		"類別":"講義",
		"英語授課":"N",
		"課程名稱 (連結課程地圖)":"光電高分子材料",
		"選必修":"選修",
		"學分":"3",
		"教師姓名 *:主負責老師":"許聯崇",
		"已選課人數 ":"16",
		"餘額 ":"33",
		"時間":"[3]3~4 [5]3",
		"教室":"唯農大樓                      7202",
		"備註":"empty",
		"限選條件":"empty",
		"業界專家參與":"否",
		"屬性碼":"MSE5024",
		"跨領域學分學程":"empty"
	},
	{
		"系所名稱":"材料所           MSE",
		"系號":"N5",
		"序號":"129",
		"課程碼":"N581400",
		"分班碼":"empty",
		"班別":"碩博",
		"年級":"empty",
		"類別":"講義",
		"英語授課":"N",
		"課程名稱 (連結課程地圖)":"奈米材料",
		"選必修":"選修",
		"學分":"3",
		"教師姓名 *:主負責老師":"洪飛義",
		"已選課人數 ":"101",
		"餘額 ":"額滿",
		"時間":"[3]5~7",
		"教室":"儀器設備大樓                  95403",
		"備註":"empty",
		"限選條件":"empty",
		"業界專家參與":"否",
		"屬性碼":"MSE",
		"跨領域學分學程":"empty"
	},
	{
		"系所名稱":"材料所           MSE",
		"系號":"N5",
		"序號":"131",
		"課程碼":"N564800",
		"分班碼":"empty",
		"班別":"碩博",
		"年級":"empty",
		"類別":"講義",
		"英語授課":"N",
		"課程名稱 (連結課程地圖)":"固態離子元件",
		"選必修":"選修",
		"學分":"3",
		"教師姓名 *:主負責老師":"方冠榮",
		"已選課人數 ":"7",
		"餘額 ":"28",
		"時間":"[3]7 [5]3~4",
		"教室":"唯農大樓                      7106",
		"備註":"empty",
		"限選條件":"empty",
		"業界專家參與":"否",
		"屬性碼":"MSE5021",
		"跨領域學分學程":"empty"
	},
	{
		"系所名稱":"材料所           MSE",
		"系號":"N5",
		"序號":"135",
		"課程碼":"N552310",
		"分班碼":"empty",
		"班別":"碩博",
		"年級":"empty",
		"類別":"講義",
		"英語授課":"Y",
		"課程名稱 (連結課程地圖)":"高等固態物理（一）",
		"選必修":"選修",
		"學分":"3",
		"教師姓名 *:主負責老師":"謝馬利歐",
		"已選課人數 ":"14",
		"餘額 ":"62",
		"時間":"[1]6~8",
		"教室":"物理二館                      49312",
		"備註":"empty",
		"限選條件":"empty",
		"業界專家參與":"否",
		"屬性碼":"MSE5003",
		"跨領域學分學程":"empty"
	},
	{
		"系所名稱":"材料所           MSE",
		"系號":"N5",
		"序號":"136",
		"課程碼":"N572900",
		"分班碼":"empty",
		"班別":"碩博",
		"年級":"empty",
		"類別":"研討",
		"英語授課":"N",
		"課程名稱 (連結課程地圖)":"材料光電子學應用",
		"選必修":"選修",
		"學分":"3",
		"教師姓名 *:主負責老師":"蘇彥勳",
		"已選課人數 ":"12",
		"餘額 ":"64",
		"時間":"[4]3~4 [5]5",
		"教室":"物理二館                      49312",
		"備註":"empty",
		"限選條件":"empty",
		"業界專家參與":"否",
		"屬性碼":"MSE",
		"跨領域學分學程":"empty"
	},
	{
		"系所名稱":"材料所           MSE",
		"系號":"N5",
		"序號":"137",
		"課程碼":"N557300",
		"分班碼":"empty",
		"班別":"碩博",
		"年級":"empty",
		"類別":"講義",
		"英語授課":"Y",
		"課程名稱 (連結課程地圖)":"固態熱力學",
		"選必修":"必修",
		"學分":"3",
		"教師姓名 *:主負責老師":"林士剛",
		"已選課人數 ":"91",
		"餘額 ":"額滿",
		"時間":"[1]2 [2]7~8",
		"教室":"唯農大樓                      7206",
		"備註":"1.外籍生優先 2.以上優先係指開放第一階段選課之學生身分",
		"限選條件":"empty",
		"業界專家參與":"否",
		"屬性碼":"MSE7001",
		"跨領域學分學程":"奈米積體電路工程碩士班學分學程"
	},
	{
		"系所名稱":"材料所           MSE",
		"系號":"N5",
		"序號":"138",
		"課程碼":"N557400",
		"分班碼":"empty",
		"班別":"碩博",
		"年級":"empty",
		"類別":"講義",
		"英語授課":"N",
		"課程名稱 (連結課程地圖)":"高等材料分析",
		"選必修":"必修",
		"學分":"3",
		"教師姓名 *:主負責老師":"劉全璞",
		"已選課人數 ":"100",
		"餘額 ":"額滿",
		"時間":"[1]5 [2]5~6",
		"教室":"物理二館                      49322",
		"備註":"1.中文授課班級：大學部非材料系及重修研究生優先 2.以上優先係指開放第一階",
		"限選條件":"empty",
		"業界專家參與":"否",
		"屬性碼":"MSE7002",
		"跨領域學分學程":"奈米積體電路工程碩士班學分學程"
	},
	{
		"系所名稱":"材料所           MSE",
		"系號":"N5",
		"序號":"139",
		"課程碼":"N557400",
		"分班碼":"2",
		"班別":"碩博",
		"年級":"empty",
		"類別":"講義",
		"英語授課":"Y",
		"課程名稱 (連結課程地圖)":"高等材料分析",
		"選必修":"必修",
		"學分":"3",
		"教師姓名 *:主負責老師":"阮至正",
		"已選課人數 ":"15",
		"餘額 ":"25",
		"時間":"[1]5 [2]5~6",
		"教室":"機械系館                      91205",
		"備註":"1.外籍生優先 2.以上優先係指開放第一階段選課之學生身分",
		"限選條件":"empty",
		"業界專家參與":"否",
		"屬性碼":"MSE7002",
		"跨領域學分學程":"奈米積體電路工程碩士班學分學程"
	}
]