[
	{
		"系所名稱":"統計所           STAT",
		"系號":"R2",
		"序號":"001",
		"課程碼":"R250610",
		"分班碼":"empty",
		"班別":"碩博一",
		"年級":"empty",
		"類別":"研討",
		"英語授課":"N",
		"課程名稱 (連結課程地圖)":"專題討論（一）",
		"選必修":"必修",
		"學分":"1",
		"教師姓名 *:主負責老師":"未定",
		"已選課人數 ":"18",
		"餘額 ":"59",
		"時間":"[4]7~8",
		"教室":"統計系館                      62331",
		"備註":"碩博合班",
		"限選條件":"empty",
		"業界專家參與":"是",
		"屬性碼":"STAT6017",
		"跨領域學分學程":"empty"
	},
	{
		"系所名稱":"統計所           STAT",
		"系號":"R2",
		"序號":"002",
		"課程碼":"R250530",
		"分班碼":"empty",
		"班別":"碩博二",
		"年級":"empty",
		"類別":"研討",
		"英語授課":"N",
		"課程名稱 (連結課程地圖)":"專題討論（三）",
		"選必修":"必修",
		"學分":"1",
		"教師姓名 *:主負責老師":"未定",
		"已選課人數 ":"14",
		"餘額 ":"63",
		"時間":"[4]7~8",
		"教室":"統計系館                      62331",
		"備註":"碩博合班",
		"限選條件":"empty",
		"業界專家參與":"是",
		"屬性碼":"STAT6021",
		"跨領域學分學程":"empty"
	},
	{
		"系所名稱":"統計所           STAT",
		"系號":"R2",
		"序號":"004",
		"課程碼":"R250111",
		"分班碼":"empty",
		"班別":"碩一",
		"年級":"1",
		"類別":"講義",
		"英語授課":"N",
		"課程名稱 (連結課程地圖)":"數理統計（一）",
		"選必修":"必選",
		"學分":"3",
		"教師姓名 *:主負責老師":"吳鐵肩",
		"已選課人數 ":"17",
		"餘額 ":"8",
		"時間":"[2]8 [1]7~8",
		"教室":"統計系館                      62451",
		"備註":"empty",
		"限選條件":"empty",
		"業界專家參與":"否",
		"屬性碼":"STAT6013",
		"跨領域學分學程":"empty"
	},
	{
		"系所名稱":"統計所           STAT",
		"系號":"R2",
		"序號":"005",
		"課程碼":"R250900",
		"分班碼":"empty",
		"班別":"碩一",
		"年級":"1",
		"類別":"講義",
		"英語授課":"N",
		"課程名稱 (連結課程地圖)":"統計方法",
		"選必修":"必選",
		"學分":"4",
		"教師姓名 *:主負責老師":"李國榮",
		"已選課人數 ":"17",
		"餘額 ":"8",
		"時間":"[1]2~3 [3]3~4",
		"教室":"統計系館                      62451",
		"備註":"empty",
		"限選條件":"empty",
		"業界專家參與":"否",
		"屬性碼":"STAT6015",
		"跨領域學分學程":"empty"
	},
	{
		"系所名稱":"統計所           STAT",
		"系號":"R2",
		"序號":"006",
		"課程碼":"R261000",
		"分班碼":"empty",
		"班別":"碩博",
		"年級":"empty",
		"類別":"講義",
		"英語授課":"N",
		"課程名稱 (連結課程地圖)":"統計諮詢專題",
		"選必修":"必選",
		"學分":"3",
		"教師姓名 *:主負責老師":"詹世煌",
		"已選課人數 ":"15",
		"餘額 ":"25",
		"時間":"[5]2~4",
		"教室":"統計系館                      62227",
		"備註":"限碩二博二以上選修",
		"限選條件":"empty",
		"業界專家參與":"否",
		"屬性碼":"STAT6023",
		"跨領域學分學程":"empty"
	},
	{
		"系所名稱":"統計所           STAT",
		"系號":"R2",
		"序號":"007",
		"課程碼":"R270310",
		"分班碼":"empty",
		"班別":"博一",
		"年級":"empty",
		"類別":"講義",
		"英語授課":"N",
		"課程名稱 (連結課程地圖)":"高等統計推論（一）",
		"選必修":"必修",
		"學分":"3",
		"教師姓名 *:主負責老師":"陳瑞彬",
		"已選課人數 ":"2",
		"餘額 ":"8",
		"時間":"[1]3 [3]3~4",
		"教室":"統計系館                      62333",
		"備註":"empty",
		"限選條件":"empty",
		"業界專家參與":"否",
		"屬性碼":"STAT9001",
		"跨領域學分學程":"empty"
	},
	{
		"系所名稱":"統計所           STAT",
		"系號":"R2",
		"序號":"008",
		"課程碼":"R251600",
		"分班碼":"empty",
		"班別":"碩博",
		"年級":"empty",
		"類別":"講義",
		"英語授課":"N",
		"課程名稱 (連結課程地圖)":"機率論",
		"選必修":"選修",
		"學分":"3",
		"教師姓名 *:主負責老師":"未定",
		"已選課人數 ":"4",
		"餘額 ":"21",
		"時間":"[4]2~4",
		"教室":"統計系館                      62451",
		"備註":"empty",
		"限選條件":"empty",
		"業界專家參與":"否",
		"屬性碼":"STAT6046",
		"跨領域學分學程":"empty"
	},
	{
		"系所名稱":"統計所           STAT",
		"系號":"R2",
		"序號":"010",
		"課程碼":"R261400",
		"分班碼":"empty",
		"班別":"碩博",
		"年級":"empty",
		"類別":"講義",
		"英語授課":"N",
		"課程名稱 (連結課程地圖)":"投資技術分析",
		"選必修":"選修",
		"學分":"3",
		"教師姓名 *:主負責老師":"吳宗正",
		"已選課人數 ":"14",
		"餘額 ":"額滿",
		"時間":"[3]7~9",
		"教室":"統計系館                      62451",
		"備註":"empty",
		"限選條件":"empty",
		"業界專家參與":"否",
		"屬性碼":"STAT6032",
		"跨領域學分學程":"empty"
	},
	{
		"系所名稱":"統計所           STAT",
		"系號":"R2",
		"序號":"011",
		"課程碼":"R252500",
		"分班碼":"empty",
		"班別":"碩博",
		"年級":"empty",
		"類別":"講義",
		"英語授課":"N",
		"課程名稱 (連結課程地圖)":"存活分析",
		"選必修":"選修",
		"學分":"3",
		"教師姓名 *:主負責老師":"未定",
		"已選課人數 ":"15",
		"餘額 ":"10",
		"時間":"[1]5~6 [3]2",
		"教室":"統計系館                      62451",
		"備註":"empty",
		"限選條件":"empty",
		"業界專家參與":"否",
		"屬性碼":"STAT6048",
		"跨領域學分學程":"empty"
	},
	{
		"系所名稱":"統計所           STAT",
		"系號":"R2",
		"序號":"012",
		"課程碼":"R252300",
		"分班碼":"empty",
		"班別":"碩博",
		"年級":"empty",
		"類別":"講義",
		"英語授課":"N",
		"課程名稱 (連結課程地圖)":"時間數列",
		"選必修":"選修",
		"學分":"3",
		"教師姓名 *:主負責老師":"黃銘欽",
		"已選課人數 ":"15",
		"餘額 ":"10",
		"時間":"[2]5~7",
		"教室":"統計系館                      62451",
		"備註":"empty",
		"限選條件":"empty",
		"業界專家參與":"否",
		"屬性碼":"STAT6047",
		"跨領域學分學程":"empty"
	},
	{
		"系所名稱":"統計所           STAT",
		"系號":"R2",
		"序號":"013",
		"課程碼":"R253900",
		"分班碼":"empty",
		"班別":"碩博",
		"年級":"empty",
		"類別":"講義",
		"英語授課":"N",
		"課程名稱 (連結課程地圖)":"管理學統計方法專題",
		"選必修":"選修",
		"學分":"3",
		"教師姓名 *:主負責老師":"高正雄",
		"已選課人數 ":"1",
		"餘額 ":"29",
		"時間":"[3]5~7",
		"教室":"統計系館                      62113",
		"備註":"empty",
		"限選條件":"empty",
		"業界專家參與":"否",
		"屬性碼":"STAT6051",
		"跨領域學分學程":"empty"
	},
	{
		"系所名稱":"統計所           STAT",
		"系號":"R2",
		"序號":"014",
		"課程碼":"RA70700",
		"分班碼":"empty",
		"班別":"碩博",
		"年級":"empty",
		"類別":"講義",
		"英語授課":"Y",
		"課程名稱 (連結課程地圖)":"企業決策方法",
		"選必修":"必修",
		"學分":"3",
		"教師姓名 *:主負責老師":"潘浙楠",
		"已選課人數 ":"14",
		"餘額 ":"31",
		"時間":"[1]9~B",
		"教室":"管理學院                      哈佛教室",
		"備註":"與IIMBA合開, 統計系為選修3學分",
		"限選條件":"第一階段不受理選課",
		"業界專家參與":"否",
		"屬性碼":"IMBA7400E",
		"跨領域學分學程":"empty"
	},
	{
		"系所名稱":"統計所           STAT",
		"系號":"R2",
		"序號":"108",
		"課程碼":"R260700",
		"分班碼":"empty",
		"班別":"碩博",
		"年級":"empty",
		"類別":"研討",
		"英語授課":"N",
		"課程名稱 (連結課程地圖)":"專題討論",
		"選必修":"必修",
		"學分":"0",
		"教師姓名 *:主負責老師":"未定",
		"已選課人數 ":"0",
		"餘額 ":"77",
		"時間":"[4]7~8",
		"教室":"統計系館                      62331",
		"備註":"博碩三以上選修, 碩博合班",
		"限選條件":"empty",
		"業界專家參與":"是",
		"屬性碼":"STAT6050",
		"跨領域學分學程":"empty"
	}
]