[
	{
		"系所名稱":"AMBA             AMBA",
		"系號":"RD",
		"序號":"101",
		"課程碼":"RD52900",
		"分班碼":"empty",
		"班別":"碩二",
		"年級":"empty",
		"類別":"講義",
		"英語授課":"N",
		"課程名稱 (連結課程地圖)":"專題討論",
		"選必修":"選修",
		"學分":"0",
		"教師姓名 *:主負責老師":"王明隆",
		"已選課人數 ":"3",
		"餘額 ":"27",
		"時間":"[2]9",
		"教室":"管理學院                      61X02",
		"備註":"限修滿畢業學分以上之AMBA學生選修",
		"限選條件":"限本系第一階段不受理選課",
		"業界專家參與":"否",
		"屬性碼":"AMBA6190",
		"跨領域學分學程":"empty"
	},
	{
		"系所名稱":"AMBA             AMBA",
		"系號":"RD",
		"序號":"103",
		"課程碼":"RD54600",
		"分班碼":"empty",
		"班別":"碩一二",
		"年級":"empty",
		"類別":"講義",
		"英語授課":"N",
		"課程名稱 (連結課程地圖)":"創新服務設計",
		"選必修":"選修",
		"學分":"2",
		"教師姓名 *:主負責老師":"陸定邦",
		"已選課人數 ":"10",
		"餘額 ":"19",
		"時間":"[2]8~9",
		"教室":"管理學院                      小哈佛教室",
		"備註":"AMBA開課，限29人選修(含外所10名)。本院創新與服務科學跨領域學程課程之一。",
		"限選條件":"受理外系人數:10人第一階段不受理選課",
		"業界專家參與":"否",
		"屬性碼":"AMBA6126",
		"跨領域學分學程":"empty"
	},
	{
		"系所名稱":"AMBA             AMBA",
		"系號":"RD",
		"序號":"104",
		"課程碼":"R064800",
		"分班碼":"empty",
		"班別":"碩一二",
		"年級":"empty",
		"類別":"講義",
		"英語授課":"N",
		"課程名稱 (連結課程地圖)":"公司財務策略個案研討",
		"選必修":"選修",
		"學分":"2",
		"教師姓名 *:主負責老師":"陳嬿如 張紹基*",
		"已選課人數 ":"34",
		"餘額 ":"15",
		"時間":"[2]A~B",
		"教室":"管理學院                      62X01",
		"備註":"EMBA/AMBA合開，限49人選修。",
		"限選條件":"限本系第一階段不受理選課",
		"業界專家參與":"否",
		"屬性碼":"EMBA6831",
		"跨領域學分學程":"empty"
	},
	{
		"系所名稱":"AMBA             AMBA",
		"系號":"RD",
		"序號":"105",
		"課程碼":"RD53800",
		"分班碼":"empty",
		"班別":"碩一二",
		"年級":"empty",
		"類別":"講義",
		"英語授課":"N",
		"課程名稱 (連結課程地圖)":"領導與溝通",
		"選必修":"選修",
		"學分":"2",
		"教師姓名 *:主負責老師":"利德江",
		"已選課人數 ":"30",
		"餘額 ":"24",
		"時間":"[4]A~B",
		"教室":"管理學院                      62X02",
		"備註":"AMBA開課，限54人選修(含外所15名)。本院創新與服務科學跨領域學程課程之一。",
		"限選條件":"受理外系人數:15人第一階段不受理選課",
		"業界專家參與":"否",
		"屬性碼":"AMBA6005",
		"跨領域學分學程":"empty"
	},
	{
		"系所名稱":"AMBA             AMBA",
		"系號":"RD",
		"序號":"106",
		"課程碼":"RD53400",
		"分班碼":"empty",
		"班別":"碩一二",
		"年級":"empty",
		"類別":"講義",
		"英語授課":"N",
		"課程名稱 (連結課程地圖)":"財務管理",
		"選必修":"選修",
		"學分":"2",
		"教師姓名 *:主負責老師":"林軒竹",
		"已選課人數 ":"17",
		"餘額 ":"12",
		"時間":"[6]2~3",
		"教室":"管理學院                      小哈佛教室",
		"備註":"雙週六上課，AMBA開課，限29人選修。",
		"限選條件":"限本系第一階段不受理選課",
		"業界專家參與":"否",
		"屬性碼":"AMBA6001",
		"跨領域學分學程":"empty"
	},
	{
		"系所名稱":"AMBA             AMBA",
		"系號":"RD",
		"序號":"107",
		"課程碼":"RD53700",
		"分班碼":"empty",
		"班別":"碩一二",
		"年級":"empty",
		"類別":"講義",
		"英語授課":"N",
		"課程名稱 (連結課程地圖)":"生產與作業管理",
		"選必修":"選修",
		"學分":"2",
		"教師姓名 *:主負責老師":"戴佐敏",
		"已選課人數 ":"29",
		"餘額 ":"額滿",
		"時間":"[6]6~7",
		"教室":"管理學院                      小哈佛教室",
		"備註":"雙週六上課，AMBA開課，限29人選修。",
		"限選條件":"限本系第一階段不受理選課",
		"業界專家參與":"否",
		"屬性碼":"AMBA6004",
		"跨領域學分學程":"empty"
	},
	{
		"系所名稱":"AMBA             AMBA",
		"系號":"RD",
		"序號":"108",
		"課程碼":"R860300",
		"分班碼":"empty",
		"班別":"碩一二",
		"年級":"empty",
		"類別":"講義",
		"英語授課":"N",
		"課程名稱 (連結課程地圖)":"期貨",
		"選必修":"選修",
		"學分":"3",
		"教師姓名 *:主負責老師":"李宏志",
		"已選課人數 ":"5",
		"餘額 ":"15",
		"時間":"[1]2~4",
		"教室":"會計系館                      63209",
		"備註":"與財金所合開",
		"限選條件":"限本系",
		"業界專家參與":"否",
		"屬性碼":"FIN6036",
		"跨領域學分學程":"empty"
	},
	{
		"系所名稱":"AMBA             AMBA",
		"系號":"RD",
		"序號":"109",
		"課程碼":"R850100",
		"分班碼":"empty",
		"班別":"碩一二",
		"年級":"empty",
		"類別":"講義",
		"英語授課":"Y",
		"課程名稱 (連結課程地圖)":"總體經濟學",
		"選必修":"必修",
		"學分":"3",
		"教師姓名 *:主負責老師":"林軒竹",
		"已選課人數 ":"32",
		"餘額 ":"18",
		"時間":"[3]2~4",
		"教室":"會計系館                      63210",
		"備註":"empty",
		"限選條件":"限本系",
		"業界專家參與":"否",
		"屬性碼":"FIN6001",
		"跨領域學分學程":"empty"
	},
	{
		"系所名稱":"AMBA             AMBA",
		"系號":"RD",
		"序號":"110",
		"課程碼":"R154200",
		"分班碼":"empty",
		"班別":"碩一二",
		"年級":"empty",
		"類別":"講義",
		"英語授課":"Y",
		"課程名稱 (連結課程地圖)":"公司治理與財務報導理論研討",
		"選必修":"選修",
		"學分":"3",
		"教師姓名 *:主負責老師":"黃華瑋",
		"已選課人數 ":"27",
		"餘額 ":"額滿",
		"時間":"[3]6~8",
		"教室":"會計系館                      63405",
		"備註":"empty",
		"限選條件":"限本系",
		"業界專家參與":"否",
		"屬性碼":"ACC7000",
		"跨領域學分學程":"empty"
	},
	{
		"系所名稱":"AMBA             AMBA",
		"系號":"RD",
		"序號":"111",
		"課程碼":"R858400",
		"分班碼":"empty",
		"班別":"碩一二",
		"年級":"empty",
		"類別":"講義",
		"英語授課":"N",
		"課程名稱 (連結課程地圖)":"時間序列研究",
		"選必修":"選修",
		"學分":"3",
		"教師姓名 *:主負責老師":"王澤世",
		"已選課人數 ":"20",
		"餘額 ":"37",
		"時間":"[3]6~8",
		"教室":"會計系館                      63404",
		"備註":"與財金所合開",
		"限選條件":"empty",
		"業界專家參與":"否",
		"屬性碼":"FIN6054",
		"跨領域學分學程":"empty"
	},
	{
		"系所名稱":"AMBA             AMBA",
		"系號":"RD",
		"序號":"112",
		"課程碼":"R856900",
		"分班碼":"empty",
		"班別":"碩一二",
		"年級":"empty",
		"類別":"講義",
		"英語授課":"N",
		"課程名稱 (連結課程地圖)":"企業社會責任與社會責任投資",
		"選必修":"選修",
		"學分":"3",
		"教師姓名 *:主負責老師":"顏盟峯",
		"已選課人數 ":"59",
		"餘額 ":"21",
		"時間":"[5]2~4",
		"教室":"會計系館                      63210",
		"備註":"與會研所合開",
		"限選條件":"限本系",
		"業界專家參與":"否",
		"屬性碼":"FIN6033",
		"跨領域學分學程":"empty"
	},
	{
		"系所名稱":"AMBA             AMBA",
		"系號":"RD",
		"序號":"113",
		"課程碼":"R662200",
		"分班碼":"empty",
		"班別":"碩一二",
		"年級":"empty",
		"類別":"講義",
		"英語授課":"N",
		"課程名稱 (連結課程地圖)":"國際行銷與策略專題",
		"選必修":"選修",
		"學分":"3",
		"教師姓名 *:主負責老師":"蔡惠婷",
		"已選課人數 ":"20",
		"餘額 ":"額滿",
		"時間":"[1]2~4",
		"教室":"國企所                        61401",
		"備註":"empty",
		"限選條件":"限本系",
		"業界專家參與":"否",
		"屬性碼":"IB7014",
		"跨領域學分學程":"empty"
	},
	{
		"系所名稱":"AMBA             AMBA",
		"系號":"RD",
		"序號":"114",
		"課程碼":"R466600",
		"分班碼":"empty",
		"班別":"碩一二",
		"年級":"empty",
		"類別":"講義",
		"英語授課":"N",
		"課程名稱 (連結課程地圖)":"計量經濟學",
		"選必修":"選修",
		"學分":"3",
		"教師姓名 *:主負責老師":"康信鴻",
		"已選課人數 ":"54",
		"餘額 ":"額滿",
		"時間":"[1]B~D",
		"教室":"企管系館                      62121",
		"備註":"與企研所、國企所合開",
		"限選條件":"限本系",
		"業界專家參與":"否",
		"屬性碼":"BA6006",
		"跨領域學分學程":"empty"
	},
	{
		"系所名稱":"AMBA             AMBA",
		"系號":"RD",
		"序號":"115",
		"課程碼":"R651700",
		"分班碼":"empty",
		"班別":"碩一二",
		"年級":"empty",
		"類別":"講義",
		"英語授課":"N",
		"課程名稱 (連結課程地圖)":"財務實証專題討論",
		"選必修":"選修",
		"學分":"3",
		"教師姓名 *:主負責老師":"江明憲",
		"已選課人數 ":"15",
		"餘額 ":"25",
		"時間":"[2]2~4",
		"教室":"企管系館                      62453",
		"備註":"與企研所、國企所合開",
		"限選條件":"限本系",
		"業界專家參與":"否",
		"屬性碼":"IB7190",
		"跨領域學分學程":"empty"
	},
	{
		"系所名稱":"AMBA             AMBA",
		"系號":"RD",
		"序號":"116",
		"課程碼":"R463500",
		"分班碼":"empty",
		"班別":"碩一二",
		"年級":"empty",
		"類別":"講義",
		"英語授課":"N",
		"課程名稱 (連結課程地圖)":"企業人力資源診斷",
		"選必修":"選修",
		"學分":"3",
		"教師姓名 *:主負責老師":"張海青",
		"已選課人數 ":"60",
		"餘額 ":"額滿",
		"時間":"[2]5~7",
		"教室":"企管系館                      62422",
		"備註":"與企研所、國企所合開",
		"限選條件":"限本系",
		"業界專家參與":"否",
		"屬性碼":"BA6009",
		"跨領域學分學程":"empty"
	},
	{
		"系所名稱":"AMBA             AMBA",
		"系號":"RD",
		"序號":"117",
		"課程碼":"R467500",
		"分班碼":"1",
		"班別":"碩一二",
		"年級":"empty",
		"類別":"講義",
		"英語授課":"N",
		"課程名稱 (連結課程地圖)":"科技商品化",
		"選必修":"選修",
		"學分":"3",
		"教師姓名 *:主負責老師":"陳淑惠",
		"已選課人數 ":"16",
		"餘額 ":"44",
		"時間":"[3]6~8",
		"教室":"企管系館                      62422",
		"備註":"empty",
		"限選條件":"限本系",
		"業界專家參與":"否",
		"屬性碼":"BA6026",
		"跨領域學分學程":"empty"
	},
	{
		"系所名稱":"AMBA             AMBA",
		"系號":"RD",
		"序號":"119",
		"課程碼":"R463300",
		"分班碼":"1",
		"班別":"碩一二",
		"年級":"empty",
		"類別":"講義",
		"英語授課":"N",
		"課程名稱 (連結課程地圖)":"策略行銷",
		"選必修":"選修",
		"學分":"3",
		"教師姓名 *:主負責老師":"蔡燿全",
		"已選課人數 ":"58",
		"餘額 ":"額滿",
		"時間":"[5]2~4",
		"教室":"企管系館                      62212",
		"備註":"empty",
		"限選條件":"限本系",
		"業界專家參與":"否",
		"屬性碼":"BA7029",
		"跨領域學分學程":"empty"
	},
	{
		"系所名稱":"AMBA             AMBA",
		"系號":"RD",
		"序號":"121",
		"課程碼":"R469100",
		"分班碼":"1",
		"班別":"碩一二",
		"年級":"empty",
		"類別":"講義",
		"英語授課":"N",
		"課程名稱 (連結課程地圖)":"管理資訊系統",
		"選必修":"選修",
		"學分":"3",
		"教師姓名 *:主負責老師":"張心馨",
		"已選課人數 ":"38",
		"餘額 ":"2",
		"時間":"[2]6~8",
		"教室":"企管系館                      62453",
		"備註":"AMBA與企管所合開",
		"限選條件":"限本系",
		"業界專家參與":"否",
		"屬性碼":"BA6007",
		"跨領域學分學程":"empty"
	}
]