[
	{
		"系所名稱":"環醫所           EOH",
		"系號":"S7",
		"序號":"001",
		"課程碼":"S750610",
		"分班碼":"1",
		"班別":"碩一",
		"年級":"empty",
		"類別":"研討",
		"英語授課":"N",
		"課程名稱 (連結課程地圖)":"專題討論（一）",
		"選必修":"必修",
		"學分":"1",
		"教師姓名 *:主負責老師":"吳致杰",
		"已選課人數 ":"11",
		"餘額 ":"49",
		"時間":"[4]5~6",
		"教室":"醫學院                        602",
		"備註":"碩一碩二合班",
		"限選條件":"empty",
		"業界專家參與":"否",
		"屬性碼":"EOH7091",
		"跨領域學分學程":"empty"
	},
	{
		"系所名稱":"環醫所           EOH",
		"系號":"S7",
		"序號":"002",
		"課程碼":"S750630",
		"分班碼":"1",
		"班別":"碩二",
		"年級":"empty",
		"類別":"研討",
		"英語授課":"N",
		"課程名稱 (連結課程地圖)":"專題討論（三）",
		"選必修":"必修",
		"學分":"1",
		"教師姓名 *:主負責老師":"吳致杰",
		"已選課人數 ":"4",
		"餘額 ":"56",
		"時間":"[4]5~6",
		"教室":"醫學院                        602",
		"備註":"碩一碩二合班",
		"限選條件":"empty",
		"業界專家參與":"否",
		"屬性碼":"EOH7093",
		"跨領域學分學程":"empty"
	},
	{
		"系所名稱":"環醫所           EOH",
		"系號":"S7",
		"序號":"003",
		"課程碼":"S761400",
		"分班碼":"1",
		"班別":"碩三延",
		"年級":"empty",
		"類別":"研討",
		"英語授課":"N",
		"課程名稱 (連結課程地圖)":"專題討論",
		"選必修":"選修",
		"學分":"0",
		"教師姓名 *:主負責老師":"吳致杰",
		"已選課人數 ":"1",
		"餘額 ":"59",
		"時間":"[4]5",
		"教室":"醫學院                        602",
		"備註":"限碩三以上選修",
		"限選條件":"empty",
		"業界專家參與":"否",
		"屬性碼":"EOH7096",
		"跨領域學分學程":"empty"
	},
	{
		"系所名稱":"環醫所           EOH",
		"系號":"S7",
		"序號":"004",
		"課程碼":"S754101",
		"分班碼":"empty",
		"班別":"碩博",
		"年級":"empty",
		"類別":"講義",
		"英語授課":"N",
		"課程名稱 (連結課程地圖)":"工業與環境衛生",
		"選必修":"必修",
		"學分":"2",
		"教師姓名 *:主負責老師":"蘇慧貞 李俊璋 蔡朋枝 林明彥",
		"已選課人數 ":"13",
		"餘額 ":"47",
		"時間":"[4]1~2",
		"教室":"醫學院                        602",
		"備註":"empty",
		"限選條件":"empty",
		"業界專家參與":"否",
		"屬性碼":"EOH7101",
		"跨領域學分學程":"empty"
	},
	{
		"系所名稱":"環醫所           EOH",
		"系號":"S7",
		"序號":"005",
		"課程碼":"S752201",
		"分班碼":"empty",
		"班別":"碩博",
		"年級":"empty",
		"類別":"講義",
		"英語授課":"N",
		"課程名稱 (連結課程地圖)":"環境毒物學",
		"選必修":"必修",
		"學分":"2",
		"教師姓名 *:主負責老師":"廖寶琦 王應然 張志欽 劉明毅*",
		"已選課人數 ":"11",
		"餘額 ":"39",
		"時間":"[3]7~8",
		"教室":"醫學院                        208",
		"備註":"empty",
		"限選條件":"empty",
		"業界專家參與":"否",
		"屬性碼":"EOH7201",
		"跨領域學分學程":"empty"
	},
	{
		"系所名稱":"環醫所           EOH",
		"系號":"S7",
		"序號":"006",
		"課程碼":"S750101",
		"分班碼":"empty",
		"班別":"碩博",
		"年級":"empty",
		"類別":"講義",
		"英語授課":"N",
		"課程名稱 (連結課程地圖)":"生物統計",
		"選必修":"必修",
		"學分":"2",
		"教師姓名 *:主負責老師":"王亮懿 李中一*",
		"已選課人數 ":"23",
		"餘額 ":"57",
		"時間":"[1]3~4",
		"教室":"醫學院                        第三講堂",
		"備註":"醫學院核心課程",
		"限選條件":"empty",
		"業界專家參與":"否",
		"屬性碼":"EOH7301",
		"跨領域學分學程":"empty"
	},
	{
		"系所名稱":"環醫所           EOH",
		"系號":"S7",
		"序號":"007",
		"課程碼":"S750200",
		"分班碼":"empty",
		"班別":"碩博",
		"年級":"empty",
		"類別":"講義",
		"英語授課":"N",
		"課程名稱 (連結課程地圖)":"流行病學",
		"選必修":"必修",
		"學分":"2",
		"教師姓名 *:主負責老師":"張志欽",
		"已選課人數 ":"22",
		"餘額 ":"38",
		"時間":"[4]3~4",
		"教室":"醫學院                        602",
		"備註":"醫學院核心課程",
		"限選條件":"empty",
		"業界專家參與":"否",
		"屬性碼":"EOH7302",
		"跨領域學分學程":"empty"
	},
	{
		"系所名稱":"環醫所           EOH",
		"系號":"S7",
		"序號":"008",
		"課程碼":"S754801",
		"分班碼":"empty",
		"班別":"碩博",
		"年級":"1",
		"類別":"講義",
		"英語授課":"N",
		"課程名稱 (連結課程地圖)":"環境與職業醫學概論",
		"選必修":"必修",
		"學分":"2",
		"教師姓名 *:主負責老師":"郭耀昌 吳政龍 郭浩然*",
		"已選課人數 ":"11",
		"餘額 ":"29",
		"時間":"[1]5~6",
		"教室":"醫學院                        302D",
		"備註":"empty",
		"限選條件":"empty",
		"業界專家參與":"否",
		"屬性碼":"EOH7401",
		"跨領域學分學程":"empty"
	},
	{
		"系所名稱":"環醫所           EOH",
		"系號":"S7",
		"序號":"010",
		"課程碼":"S754910",
		"分班碼":"empty",
		"班別":"碩博",
		"年級":"empty",
		"類別":"講義",
		"英語授課":"N",
		"課程名稱 (連結課程地圖)":"高等環境測定（一）",
		"選必修":"選修",
		"學分":"3",
		"教師姓名 *:主負責老師":"蘇慧貞 李俊璋 蔡朋枝 林明彥",
		"已選課人數 ":"1",
		"餘額 ":"39",
		"時間":"[1]7~A",
		"教室":"醫學院                        302D",
		"備註":"empty",
		"限選條件":"empty",
		"業界專家參與":"否",
		"屬性碼":"EOH7102",
		"跨領域學分學程":"empty"
	},
	{
		"系所名稱":"環醫所           EOH",
		"系號":"S7",
		"序號":"011",
		"課程碼":"S780500",
		"分班碼":"empty",
		"班別":"碩博",
		"年級":"empty",
		"類別":"講義",
		"英語授課":"N",
		"課程名稱 (連結課程地圖)":"環境毒物健康風險評估",
		"選必修":"選修",
		"學分":"2",
		"教師姓名 *:主負責老師":"李俊璋",
		"已選課人數 ":"2",
		"餘額 ":"38",
		"時間":"[2]5~6",
		"教室":"醫學院                        203D",
		"備註":"empty",
		"限選條件":"empty",
		"業界專家參與":"否",
		"屬性碼":"EOH7109",
		"跨領域學分學程":"empty"
	},
	{
		"系所名稱":"環醫所           EOH",
		"系號":"S7",
		"序號":"012",
		"課程碼":"S771500",
		"分班碼":"empty",
		"班別":"碩博",
		"年級":"empty",
		"類別":"講義",
		"英語授課":"N",
		"課程名稱 (連結課程地圖)":"環境荷爾蒙",
		"選必修":"選修",
		"學分":"2",
		"教師姓名 *:主負責老師":"李俊璋",
		"已選課人數 ":"0",
		"餘額 ":"40",
		"時間":"[2]3~4",
		"教室":"醫學院                        202D",
		"備註":"empty",
		"限選條件":"empty",
		"業界專家參與":"否",
		"屬性碼":"EOH7111",
		"跨領域學分學程":"empty"
	},
	{
		"系所名稱":"環醫所           EOH",
		"系號":"S7",
		"序號":"014",
		"課程碼":"S755410",
		"分班碼":"empty",
		"班別":"碩博",
		"年級":"empty",
		"類別":"講義",
		"英語授課":"N",
		"課程名稱 (連結課程地圖)":"實驗毒理學（一）",
		"選必修":"選修",
		"學分":"2",
		"教師姓名 *:主負責老師":"王應然",
		"已選課人數 ":"3",
		"餘額 ":"57",
		"時間":"[2]5~6",
		"教室":"醫學院                        304D",
		"備註":"empty",
		"限選條件":"empty",
		"業界專家參與":"否",
		"屬性碼":"EOH7202",
		"跨領域學分學程":"empty"
	},
	{
		"系所名稱":"環醫所           EOH",
		"系號":"S7",
		"序號":"015",
		"課程碼":"S753010",
		"分班碼":"empty",
		"班別":"碩博",
		"年級":"empty",
		"類別":"講義",
		"英語授課":"N",
		"課程名稱 (連結課程地圖)":"化學癌瘤（一）",
		"選必修":"選修",
		"學分":"2",
		"教師姓名 *:主負責老師":"王應然",
		"已選課人數 ":"3",
		"餘額 ":"32",
		"時間":"[2]3~4",
		"教室":"醫學院                        301D",
		"備註":"empty",
		"限選條件":"empty",
		"業界專家參與":"否",
		"屬性碼":"EOH7204",
		"跨領域學分學程":"empty"
	},
	{
		"系所名稱":"環醫所           EOH",
		"系號":"S7",
		"序號":"016",
		"課程碼":"L360200",
		"分班碼":"empty",
		"班別":"碩博",
		"年級":"empty",
		"類別":"講義",
		"英語授課":"N",
		"課程名稱 (連結課程地圖)":"質譜學",
		"選必修":"選修",
		"學分":"3",
		"教師姓名 *:主負責老師":"廖寶琦",
		"已選課人數 ":"37",
		"餘額 ":"23",
		"時間":"[1]6~8",
		"教室":"醫學院                        304D",
		"備註":"環醫所化學所合班",
		"限選條件":"empty",
		"業界專家參與":"否",
		"屬性碼":"CHEM8024",
		"跨領域學分學程":"empty"
	},
	{
		"系所名稱":"環醫所           EOH",
		"系號":"S7",
		"序號":"017",
		"課程碼":"S155500",
		"分班碼":"Y",
		"班別":"碩博",
		"年級":"empty",
		"類別":"講義",
		"英語授課":"N",
		"課程名稱 (連結課程地圖)":"蛋白質體學之原理與應用",
		"選必修":"選修",
		"學分":"2",
		"教師姓名 *:主負責老師":"廖寶琦*",
		"已選課人數 ":"0",
		"餘額 ":"60",
		"時間":"未定",
		"教室":"醫學院                        602",
		"備註":"生科中心暑期課程",
		"限選條件":"empty",
		"業界專家參與":"否",
		"屬性碼":"BIMB6522",
		"跨領域學分學程":"empty"
	},
	{
		"系所名稱":"環醫所           EOH",
		"系號":"S7",
		"序號":"018",
		"課程碼":"S155900",
		"分班碼":"Y",
		"班別":"碩博",
		"年級":"empty",
		"類別":"實習",
		"英語授課":"N",
		"課程名稱 (連結課程地圖)":"蛋白質體在疾病標誌開發之應用",
		"選必修":"選修",
		"學分":"1",
		"教師姓名 *:主負責老師":"廖寶琦*",
		"已選課人數 ":"1",
		"餘額 ":"23",
		"時間":"未定",
		"教室":"醫學院                        0401",
		"備註":"２樓實驗室81-0202，生科中心暑期課程",
		"限選條件":"empty",
		"業界專家參與":"否",
		"屬性碼":"BIMB6524",
		"跨領域學分學程":"生物科技學程"
	},
	{
		"系所名稱":"環醫所           EOH",
		"系號":"S7",
		"序號":"020",
		"課程碼":"S755510",
		"分班碼":"empty",
		"班別":"碩博",
		"年級":"empty",
		"類別":"講義",
		"英語授課":"N",
		"課程名稱 (連結課程地圖)":"分子流行病學（一）",
		"選必修":"選修",
		"學分":"2",
		"教師姓名 *:主負責老師":"張志欽",
		"已選課人數 ":"2",
		"餘額 ":"38",
		"時間":"[3]1~2",
		"教室":"醫學院                        203D",
		"備註":"empty",
		"限選條件":"empty",
		"業界專家參與":"否",
		"屬性碼":"EOH7307",
		"跨領域學分學程":"empty"
	},
	{
		"系所名稱":"環醫所           EOH",
		"系號":"S7",
		"序號":"021",
		"課程碼":"S753610",
		"分班碼":"empty",
		"班別":"碩一二",
		"年級":"empty",
		"類別":"講義",
		"英語授課":"N",
		"課程名稱 (連結課程地圖)":"職業病個案診斷研究（一）",
		"選必修":"選修",
		"學分":"1",
		"教師姓名 *:主負責老師":"郭浩然",
		"已選課人數 ":"1",
		"餘額 ":"39",
		"時間":"[1]1",
		"教室":"醫學院                        302D",
		"備註":"職業病個案診斷研究(一)(三)和環境與職業醫學實例討論(一)(三)合班",
		"限選條件":"empty",
		"業界專家參與":"否",
		"屬性碼":"EOH6401",
		"跨領域學分學程":"empty"
	},
	{
		"系所名稱":"環醫所           EOH",
		"系號":"S7",
		"序號":"022",
		"課程碼":"S753630",
		"分班碼":"empty",
		"班別":"碩一二",
		"年級":"empty",
		"類別":"講義",
		"英語授課":"N",
		"課程名稱 (連結課程地圖)":"職業病個案診斷研究（三）",
		"選必修":"選修",
		"學分":"1",
		"教師姓名 *:主負責老師":"郭浩然",
		"已選課人數 ":"0",
		"餘額 ":"40",
		"時間":"[1]1",
		"教室":"醫學院                        302D",
		"備註":"職業病個案診斷研究(一)(三)和環境與職業醫學實例討論(一)(三)合班",
		"限選條件":"empty",
		"業界專家參與":"否",
		"屬性碼":"EOH6403",
		"跨領域學分學程":"empty"
	},
	{
		"系所名稱":"環醫所           EOH",
		"系號":"S7",
		"序號":"023",
		"課程碼":"S760910",
		"分班碼":"empty",
		"班別":"碩博",
		"年級":"empty",
		"類別":"實習",
		"英語授課":"N",
		"課程名稱 (連結課程地圖)":"環境與職業醫學實習（一）",
		"選必修":"選修",
		"學分":"1",
		"教師姓名 *:主負責老師":"郭浩然",
		"已選課人數 ":"1",
		"餘額 ":"39",
		"時間":"[3]2~4",
		"教室":"empty",
		"備註":"醫院門診",
		"限選條件":"empty",
		"業界專家參與":"否",
		"屬性碼":"EOH7403",
		"跨領域學分學程":"empty"
	},
	{
		"系所名稱":"環醫所           EOH",
		"系號":"S7",
		"序號":"101",
		"課程碼":"S750610",
		"分班碼":"2",
		"班別":"博一",
		"年級":"empty",
		"類別":"研討",
		"英語授課":"N",
		"課程名稱 (連結課程地圖)":"專題討論（一）",
		"選必修":"必修",
		"學分":"1",
		"教師姓名 *:主負責老師":"吳致杰",
		"已選課人數 ":"1",
		"餘額 ":"59",
		"時間":"[4]9~A",
		"教室":"醫學院                        602",
		"備註":"博一博二合班",
		"限選條件":"empty",
		"業界專家參與":"否",
		"屬性碼":"EOH7091",
		"跨領域學分學程":"empty"
	},
	{
		"系所名稱":"環醫所           EOH",
		"系號":"S7",
		"序號":"102",
		"課程碼":"S770210",
		"分班碼":"empty",
		"班別":"博一",
		"年級":"empty",
		"類別":"實習",
		"英語授課":"N",
		"課程名稱 (連結課程地圖)":"教學實習（一）",
		"選必修":"必修",
		"學分":"0",
		"教師姓名 *:主負責老師":"郭浩然",
		"已選課人數 ":"1",
		"餘額 ":"39",
		"時間":"未定",
		"教室":"empty",
		"備註":"擔任課程助教",
		"限選條件":"empty",
		"業界專家參與":"否",
		"屬性碼":"EOH9001",
		"跨領域學分學程":"empty"
	},
	{
		"系所名稱":"環醫所           EOH",
		"系號":"S7",
		"序號":"103",
		"課程碼":"S750630",
		"分班碼":"2",
		"班別":"博二",
		"年級":"empty",
		"類別":"研討",
		"英語授課":"N",
		"課程名稱 (連結課程地圖)":"專題討論（三）",
		"選必修":"必修",
		"學分":"1",
		"教師姓名 *:主負責老師":"吳致杰",
		"已選課人數 ":"0",
		"餘額 ":"60",
		"時間":"[4]9~A",
		"教室":"醫學院                        602",
		"備註":"博一博二合班",
		"限選條件":"empty",
		"業界專家參與":"否",
		"屬性碼":"EOH7093",
		"跨領域學分學程":"empty"
	},
	{
		"系所名稱":"環醫所           EOH",
		"系號":"S7",
		"序號":"104",
		"課程碼":"S770230",
		"分班碼":"empty",
		"班別":"博二",
		"年級":"empty",
		"類別":"實習",
		"英語授課":"N",
		"課程名稱 (連結課程地圖)":"教學實習（三）",
		"選必修":"必修",
		"學分":"0",
		"教師姓名 *:主負責老師":"郭浩然",
		"已選課人數 ":"0",
		"餘額 ":"40",
		"時間":"未定",
		"教室":"empty",
		"備註":"擔任課程助教",
		"限選條件":"empty",
		"業界專家參與":"否",
		"屬性碼":"EOH9003",
		"跨領域學分學程":"empty"
	},
	{
		"系所名稱":"環醫所           EOH",
		"系號":"S7",
		"序號":"105",
		"課程碼":"S761400",
		"分班碼":"2",
		"班別":"博三延",
		"年級":"empty",
		"類別":"研討",
		"英語授課":"N",
		"課程名稱 (連結課程地圖)":"專題討論",
		"選必修":"選修",
		"學分":"0",
		"教師姓名 *:主負責老師":"吳致杰",
		"已選課人數 ":"1",
		"餘額 ":"59",
		"時間":"[4]9",
		"教室":"醫學院                        602",
		"備註":"限博三以上選修",
		"限選條件":"empty",
		"業界專家參與":"否",
		"屬性碼":"EOH7096",
		"跨領域學分學程":"empty"
	},
	{
		"系所名稱":"環醫所           EOH",
		"系號":"S7",
		"序號":"108",
		"課程碼":"S770910",
		"分班碼":"empty",
		"班別":"博一二",
		"年級":"empty",
		"類別":"講義",
		"英語授課":"N",
		"課程名稱 (連結課程地圖)":"環境與職業醫學實例討論（一）",
		"選必修":"選修",
		"學分":"1",
		"教師姓名 *:主負責老師":"郭浩然",
		"已選課人數 ":"0",
		"餘額 ":"60",
		"時間":"[1]2",
		"教室":"醫學院                        302D",
		"備註":"職業病個案診斷研究(一)(三)和環境與職業醫學實例討論(一)(三)合班",
		"限選條件":"empty",
		"業界專家參與":"否",
		"屬性碼":"EOH9009",
		"跨領域學分學程":"empty"
	},
	{
		"系所名稱":"環醫所           EOH",
		"系號":"S7",
		"序號":"109",
		"課程碼":"S770930",
		"分班碼":"empty",
		"班別":"博一二",
		"年級":"empty",
		"類別":"講義",
		"英語授課":"N",
		"課程名稱 (連結課程地圖)":"環境與職業醫學實例討論（三）",
		"選必修":"選修",
		"學分":"1",
		"教師姓名 *:主負責老師":"郭浩然",
		"已選課人數 ":"0",
		"餘額 ":"40",
		"時間":"[1]2",
		"教室":"醫學院                        302D",
		"備註":"職業病個案診斷研究(一)(三)與環境與職業醫學實例討論(一)(三)合班",
		"限選條件":"empty",
		"業界專家參與":"否",
		"屬性碼":"EOH9011",
		"跨領域學分學程":"empty"
	}
]